{
  "phone": "994507142403",
  "forms": [
    {
      "title": "U\u015fa\u011f\u0131ma \u00f6z\u0259l mahn\u0131",
      "video": "https://www.instagram.com/reel/Cr1234567890/",
      "questions": [
        "Ad\u0131 n\u0259dir?",
        "Sevdiyi oyunca\u011f\u0131 n\u0259dir?"
      ]
    },
    {
      "title": "C\u00fctl\u00fck \u00fc\u00e7\u00fcn sevgi mahn\u0131s\u0131",
      "video": "https://example.com/video2.mp4",
      "questions": [
        "Adlar\u0131 n\u0259dir?",
        "\u0130lk tan\u0131\u015f olduqlar\u0131 tarix?"
      ]
    }
  ]
}